myfunctions_nadiaconeaev89/__init__.py
myfunctions_nadiaconeaev89/math.py
myfunctions_nadiaconeaev89-0.0.10.dist-info/METADATA
myfunctions_nadiaconeaev89-0.0.10.dist-info/WHEEL
myfunctions_nadiaconeaev89-0.0.10.dist-info/top_level.txt
myfunctions_nadiaconeaev89-0.0.10.dist-info/RECORD
