Metadata-Version: 2.1
Name: myfunctions_nadiaconeaev89
Version: 0.0.10
Summary: A description of your package
Home-page: https://github.com/nadiaconeaev89/
Author: Nadejda Coneaev
Author-email: nadejda.savin@gmail.com
License: MIT
Platform: UNKNOWN
Classifier: Programming Language :: Python :: 3
Classifier: License :: OSI Approved :: MIT License
Classifier: Operating System :: OS Independent
Requires-Python: >=3.6
